ftrack_framework_core/__init__.py
ftrack_framework_core/asset/__init__.py
ftrack_framework_core/asset/asset_info.py
ftrack_framework_core/asset/dcc_object.py
ftrack_framework_core/client/__init__.py
ftrack_framework_core/client/host_connection.py
ftrack_framework_core/configure_logging.py
ftrack_framework_core/engine/__init__.py
ftrack_framework_core/event/__init__.py
ftrack_framework_core/exceptions/__init__.py
ftrack_framework_core/exceptions/engine.py
ftrack_framework_core/exceptions/plugin.py
ftrack_framework_core/host/__init__.py
ftrack_framework_core/log/__init__.py
ftrack_framework_core/log/log_item.py
ftrack_framework_core/plugin/__init__.py
ftrack_framework_core/plugin/plugin_info.py
ftrack_framework_core/registry/__init__.py
ftrack_framework_core/widget/__init__.py
ftrack_framework_core/widget/dialog.py
ftrack_framework_core/widget/widget.py
ftrack_framework_core-3.2.0.dist-info/LICENSE.txt
ftrack_framework_core-3.2.0.dist-info/METADATA
ftrack_framework_core-3.2.0.dist-info/WHEEL
ftrack_framework_core-3.2.0.dist-info/RECORD
